classification_service/__init__.py
classification_service/app.py
classification_service/health.py
classification_service-0.1.2.dist-info/WHEEL
classification_service-0.1.2.dist-info/METADATA
classification_service-0.1.2.dist-info/RECORD
