Metadata-Version: 2.1
Name: classification-service
Version: 0.1.2
Summary: 
Author: pvasisht
Author-email: prajwal_prakashvasisht@intuit.com
Requires-Python: >=3.7,<4.0
Classifier: Programming Language :: Python :: 3
Classifier: Programming Language :: Python :: 3.7
Classifier: Programming Language :: Python :: 3.8
Classifier: Programming Language :: Python :: 3.9
Requires-Dist: flask
